Workbook

Sheet MASTER
A2: Head of Account | B2: Address | C2: Address | D2: Phone | E2: City | F2: GST # | G2: PAN | H2: State | I2: pincode
A3: .Kulvir Singh | B3: Aadhar Card No. 781828029617 | D3: =IFERROR(VLOOKUP(A3, Sheet2!A:C, 3, FALSE), "") | E3: Ludhiana | H3: PUNJAB | I3: 141001
A4: 50 Shades | B4: Awantipora | D4: =IFERROR(VLOOKUP(A4, Sheet2!A:B, 2, FALSE), "") | E4: Awantipora | H4: JAMMU & KASHMIR | I4: 192122 | J4: Jammu
A5: A K Traders | B5: Chd Landran Road | D5: =IFERROR(VLOOKUP(A5, Sheet2!A:B, 2, FALSE), "") | E5: Sector-77 | F5: 03AAHPV4566B1ZS | G5: AAHPV4566B | H5: PUNJAB | I5: 140308 | J5: Sas Nagar
A6: A M Multi Packaging Private Limited | B6: Plot No. 34 Hsiidc | C6: SECTOR-56 | D6: =IFERROR(VLOOKUP(A6, Sheet2!A:B, 2, FALSE), "") | E6: Kundli | F6: 06AAICA1075C1Z5 | G6: AAICA1075C | H6: HARYANA | I6: 131028 | J6: Sonipat
A7: A S Associates | B7: Ranbirsinghpora | C7: =IFERROR(VLOOKUP(A8, Sheet2!A:B, 2, FALSE), "") | D7: =IFERROR(VLOOKUP(A7, Sheet2!A:B, 2, FALSE), "") | E7: Jammu | F7: 01ACBFA0779R1Z8 | G7: ACBFA0779R | H7: JAMMU & KASHMIR | I7: 181102 | J7: Jammu
A8: A-1 Industries | B8: A-1 Industries | C8: Near Shiv Oil Company Bpcl Petrol Pump | E8: Khanna | F8: 03ABZPG5414E1ZS | G8: ABZPG5414E | H8: PUNJAB | I8: 141401 | J8: Ludhiana
A9: A-one Tex Tech Pvt. Ltd. | B9: Plot No-2046 | C9: Phase-ii | D9: =IFERROR(VLOOKUP(A9, Sheet2!A:B, 2, FALSE), "") | E9: Sonipat | F9: 06AAJCA4367Q1Z2 | G9: AAJCA4367Q | H9: HARYANA | I9: 131029 | J9: Sonipat
A10: A.D LOGISTICS LDH | B10: CHHATTISGARH | D10: =IFERROR(VLOOKUP(A10, Sheet2!A:B, 2, FALSE), "") | F10: 07ACAFA9584F1Z9 | G10: ACAFA9584F | H10: DELHI
A11: A.V TEXTILES | B11: M.B.D MAKT. SHOP NO.12, | C11: NEAR CIVIL HOSPITAL, | D11: =IFERROR(VLOOKUP(A11, Sheet2!A:B, 2, FALSE), "") | E11: Jalandhar | F11: 03AECPG8013K1ZV | G11: AECPG8013K | H11: PUNJAB | I11: 144001 | J11: Jalandhar
A12: A.a.packaging | B12: 275 | D12: =IFERROR(VLOOKUP(A12, Sheet2!A:B, 2, FALSE), "") | E12: Vasant Vihar,karnal | F12: 06ABIFA9469L1ZS | G12: ABIFA9469L | H12: HARYANA | I12: 132001 | J12: Karnal
A13: Aastha Marketing | B13: 1, INFRONT OF SIVAM PALACE | C13: Jawahar Nagar Bichhiya | D13: =IFERROR(VLOOKUP(A13, Sheet2!A:B, 2, FALSE), "") -> 9993560225 | E13: Rewa | F13: 23BWRPK0849P1ZU | G13: BWRPK0849P | H13: MADHYA PRADESH | I13: 486001 | J13: Rewa
A14: Abaan Packaging | B14: 04/2500-2507,,NANI BEGUMWADI, | C14: Near Mukti Dham Mandir | D14: =IFERROR(VLOOKUP(A14, Sheet2!A:B, 2, FALSE), "") -> 9825776004 | E14: Salabatpura | F14: 24AGUPC3612L1ZC | G14: AGUPC3612L | H14: GUJRAT | I14: 395003 | J14: Surat
A15: Abhishek Transport Corporation | B15: Abhishek Transport Corporation | C15: Transpoprt Nagar | D15: =IFERROR(VLOOKUP(A15, Sheet2!A:B, 2, FALSE), "") | E15: Ludhiana | F15: 03AGJPK5039N2Z5 | G15: AGJPK5039N | H15: PUNJAB | I15: 141008 | J15: Ludhiana
A16: Abr Parcel Service | B16: B-23/2818 | D16: =IFERROR(VLOOKUP(A16, Sheet2!A:B, 2, FALSE), "") | E16: Transport Nagar | F16: 03ABZPC2933Q1Z5 | G16: ABZPC2933Q | H16: PUNJAB | I16: 141003 | J16: Ludhiana
A17: Ace International | B17: 154, Cycle Shopping Centre | C17: Gill Road | D17: =IFERROR(VLOOKUP(A17, Sheet2!A:B, 2, FALSE), "") | E17: Ludhiana | F17: 03AEVPG1115M1ZJ | G17: AEVPG1115M | H17: PUNJAB | I17: 141003 | J17: Ludhiana
A18: Aditi Enterprises | D18: =IFERROR(VLOOKUP(A18, Sheet2!A:B, 2, FALSE), "") | H18: PUNJAB
A19: Aditya Creations | B19: Sadar Bazar | D19: =IFERROR(VLOOKUP(A19, Sheet2!A:B, 2, FALSE), "") | E19: Shahjahanpur | F19: 09JSMPK2274K1Z0 | G19: JSMPK2274K | H19: UTTAR PRADESH | I19: 242001 | J19: Shahjahanpur
A20: Aditya Nonwoven Fabrics Private Limited | B20: Plot No 18 | C20: Sector 21 | D20: =IFERROR(VLOOKUP(A20, Sheet2!A:B, 2, FALSE), "") | E20: Bhiwani | F20: 06AAJCA2941C1Z3 | G20: AAJCA2941C | H20: HARYANA | I20: 127021 | J20: Bhiwani
A21: Advance Tax / TDS | D21: =IFERROR(VLOOKUP(A21, Sheet2!A:B, 2, FALSE), "")
A22: Advertisment | D22: =IFERROR(VLOOKUP(A22, Sheet2!A:B, 2, FALSE), "")
A23: Agam Textile | B23: Khasra No. 886/130 | C23: Agam Textile | D23: =IFERROR(VLOOKUP(A23, Sheet2!A:B, 2, FALSE), "") | E23: Jalandhar | F23: 03BLAPS0025B1Z0 | G23: BLAPS0025B | H23: PUNJAB | I23: 144002 | J23: Jalandhar
A24: Aggarwal Hosiery Factory | B24: 7078 | C24: Guru Nanak Gali, Ashok Bazar | D24: =IFERROR(VLOOKUP(A24, Sheet2!A:B, 2, FALSE), "") | E24: Delhi | F24: 07AOHPK2987H1ZL | G24: AOHPK2987H | H24: DELHI | I24: 110031 | J24: North East Delhi
A25: Aggarwal Trading Company | B25: Shop | C25: Aggarwal Trading Company | D25: =IFERROR(VLOOKUP(A25, Sheet2!A:B, 2, FALSE), "") | E25: Village Kumbra Near Forest Complex | F25: 03CTTPM8819B1ZG | G25: CTTPM8819B | H25: PUNJAB | I25: 140308 | J25: Sas Nagar
A26: Agrimtechzone | B26: 98880-01691 | C26: MAIN BAZAR,NEAR POST OFFICE | D26: =IFERROR(VLOOKUP(A26, Sheet2!A:B, 2, FALSE), "") | E26: Pathankot | F26: 03AEJPM3993H1ZA | G26: AEJPM3993H | H26: PUNJAB | I26: 145001 | J26: Pathankot
A27: Ahuja Dresses | B27: Karan Adhaar No. 514443109565 | C27: St No. 6/2 Lajpat Nagar,Bajra | D27: =IFERROR(VLOOKUP(A27, Sheet2!A:B, 2, FALSE), "") | E27: Ludhiana | H27: PUNJAB | I27: 141007
A28: Ahuja Garments | B28: RAILWAY ROAD, BARARA | D28: =IFERROR(VLOOKUP(A28, Sheet2!A:B, 2, FALSE), "") | E28: Barara | F28: 06ADZPS0684G1ZW | G28: ADZPS0684G | H28: HARYANA | I28: 133201 | J28: Ambala
A29: Ahuja Sons | B29: Shop.no.b-16-59/85 | C29: Ahuja Sons | D29: =IFERROR(VLOOKUP(A29, Sheet2!A:B, 2, FALSE), "") | E29: Ahluwalia Street | F29: 03ACJPA0936C1ZF | G29: ACJPA0936C | H29: PUNJAB | I29: 141001 | J29: Ludhiana
A30: Air Conditioner | D30: =IFERROR(VLOOKUP(A30, Sheet2!A:B, 2, FALSE), "")
A31: Aira Knitwears | B31: B-5-617 | C31: Wait Ganj | D31: =IFERROR(VLOOKUP(A31, Sheet2!A:B, 2, FALSE), "") -> 8360316861 | E31: Ludhiana | F31: 03BUIPS4332J1ZJ | G31: BUIPS4332J | H31: PUNJAB | I31: 141008 | J31: Ludhiana
A32: Ajanta Collections | B32: Sirsa | D32: =IFERROR(VLOOKUP(A32, Sheet2!A:B, 2, FALSE), "") | E32: Rori Bazar | F32: 06AAKFA1451B1Z3 | G32: AAKFA1451B | H32: HARYANA | I32: 125055 | J32: Sirsa
A33: Ajay Bags Manufacturer | B33: 124 | D33: =IFERROR(VLOOKUP(A33, Sheet2!A:B, 2, FALSE), "") -> 8250125512 | E33: Kolkata | F33: 19DMXPP0113D1ZY | G33: DMXPP0113D | H33: WEST BENGAL | I33: 700083 | J33: North Twenty Four Pargana
A34: Ajay Hardware Sanitary House | B34: 48/10 | D34: =IFERROR(VLOOKUP(A34, Sheet2!A:B, 2, FALSE), "") | E34: Payal | F34: 03AIWPK1286E1Z6 | G34: AIWPK1286E | H34: PUNJAB | I34: 141002 | J34: Ludhiana
A35: Ajeet Arts | B35: 406 | C35: Reena Apartment | D35: =IFERROR(VLOOKUP(A35, Sheet2!A:B, 2, FALSE), "") -> 9820427369 | E35: Malad West | F35: 27AMYPS0324H1ZN | G35: AMYPS0324H | H35: MAHARASHTRA | I35: 400064 | J35: Mumbai Suburban
A36: Ajit Goods Carrier | B36: Namaste Chowk | D36: =IFERROR(VLOOKUP(A36, Sheet2!A:B, 2, FALSE), "") | E36: Karnal | F36: 06BDOPS3894N1ZH | G36: BDOPS3894N | H36: HARYANA | I36: 132001 | J36: Karnal
A37: Ajit Mills (ams) | B37: Village Nicchi Mangli | C37: Chd. Road | D37: =IFERROR(VLOOKUP(A37, Sheet2!A:B, 2, FALSE), "") -> 9261240004 | E37: Ludhiana | F37: 03AAEPH8526Q1ZE | G37: AAEPH8526Q | H37: PUNJAB | I37: 141010 | J37: Ludhiana
A38: Ajooni Biotech Limited | B38: Near Gaib Di Pully | C38: Phase Vii | D38: =IFERROR(VLOOKUP(A38, Sheet2!A:B, 2, FALSE), "") | E38: Khanna | F38: 03AAMCA2765P1Z9 | G38: AAMCA2765P | H38: PUNJAB | I38: 141401 | J38: Ludhiana
A39: Akaal Sahai Enterprises | B39: 17A RAM NAGAR | D39: =IFERROR(VLOOKUP(A39, Sheet2!A:B, 2, FALSE), "") | E39: Ambala Cantt | F39: 06AKPPS6084D1ZR | G39: AKPPS6084D | H39: HARYANA | I39: 133001 | J39: Ambala
A40: Akanksha Fabrics | B40: Village Ayali Khurd | C40: Hambran Road | D40: =IFERROR(VLOOKUP(A40, Sheet2!A:B, 2, FALSE), "") -> 9779160685 | E40: Ludhiana | F40: 03AAFFA1911P1ZO | G40: AAFFA1911P | H40: PUNJAB | I40: 141001 | J40: Ludhiana
A41: Al-qamar Graphics | B41: MURRAN CHOWK | D41: 9103101774 | E41: Pulwama | F41: 01ABSFA0055A1Z7 | G41: ABSFA0055A | H41: JAMMU & KASHMIR | I41: 192301 | J41: Pulwama
A42: All Well Trends | B42: No 8-713/18 | C42: Sangam Complex | D42: =IFERROR(VLOOKUP(A42, Sheet2!A:B, 2, FALSE), "") | E42: Kalaburagi | F42: 29AHHPR1997F1ZR | G42: AHHPR1997F | H42: KARNATKA | I42: 585101 | J42: Kalaburagi
A43: Aman Trading Company | B43: B-3-269 | C43: Purana Bazar | D43: =IFERROR(VLOOKUP(A43, Sheet2!A:B, 2, FALSE), "") | E43: Ludhiana | F43: 03BBLPS4239J1ZD | G43: BBLPS4239J | H43: PUNJAB | I43: 141008 | J43: Ludhiana
A44: Amanpreet Singh | D44: =IFERROR(VLOOKUP(A44, Sheet2!A:B, 2, FALSE), "") | H44: PUNJAB
A45: Amanpreet Singh (Supplier) | D45: =IFERROR(VLOOKUP(A45, Sheet2!A:B, 2, FALSE), "") | H45: PUNJAB
A46: Amar Kailash Enterprises | B46: B-xi-1316 | C46: Bhai Hari Singh Nagar | D46: =IFERROR(VLOOKUP(A46, Sheet2!A:B, 2, FALSE), "") | E46: Ludhiana | F46: 03AMZPM7596E1ZC | G46: AMZPM7596E | H46: PUNJAB | I46: 141008 | J46: Ludhiana
A47: Amar Photo Studio | B47: 1 | D47: =IFERROR(VLOOKUP(A47, Sheet2!A:B, 2, FALSE), "") | E47: Palampur | F47: 02EMXPS3109H1ZR | G47: EMXPS3109H | H47: HIMACHAL PRADESH | I47: 176061 | J47: Kangra
A48: Amar Transport Logistic | B48: Vishal Nagar | D48: =IFERROR(VLOOKUP(A48, Sheet2!A:B, 2, FALSE), "") | E48: Bathinda | F48: 03AAUHM6855R1Z4 | G48: AAUHM6855R | H48: PUNJAB | I48: 151001 | J48: Bathinda
A49: Ambala Goods Booking Agency | B49: T | C49: T | D49: =IFERROR(VLOOKUP(A49, Sheet2!A:B, 2, FALSE), "") | F49: 03ADTPS1375A1ZM | G49: ADTPS1375A | H49: PUNJAB | J49: T
A50: Amijara Plastics | B50: B Flat 201 Akaash Ganga | C50: DEVCHAND NAGAR, | D50: =IFERROR(VLOOKUP(A50, Sheet2!A:B, 2, FALSE), "") | E50: Thane | F50: 27AUIPS6885R1Z8 | G50: AUIPS6885R | H50: MAHARASHTRA | I50: 401101 | J50: Thane
A51: Amin-bin-khalik Impex (abk Impex) | B51: ABK HOUSE 104 | C51: ROSEENCLAVE SANAT NAGAR | D51: 9906598692 | E51: Srinagar | F51: 01ABTFA0031B1ZC | G51: ABTFA0031B | H51: JAMMU & KASHMIR | I51: 190001 | J51: Srinagar
A52: Amit Kumar | D52: =IFERROR(VLOOKUP(A52, Sheet2!A:B, 2, FALSE), "") | E52: Khanna
A53: Amit Kumar (Salesman) | D53: =IFERROR(VLOOKUP(A53, Sheet2!A:B, 2, FALSE), "") | H53: PUNJAB
A54: Amit Kumar (Supplier) | D54: =IFERROR(VLOOKUP(A54, Sheet2!A:B, 2, FALSE), "") | H54: PUNJAB
A55: Amit Kumar Morya(Supplier) | D55: =IFERROR(VLOOKUP(A55, Sheet2!A:B, 2, FALSE), "") | H55: PUNJAB
A56: Amrish Sharma | D56: =IFERROR(VLOOKUP(A56, Sheet2!A:B, 2, FALSE), "") | E56: Khanna
A57: Amrit Electro World | D57: =IFERROR(VLOOKUP(A57, Sheet2!A:B, 2, FALSE), "") | E57: Khanna | F57: 03DOPPS9117Q1ZZ | G57: DOPPS9117Q | H57: PUNJAB | I57: 141401 | J57: Ludhiana
A58: Amrit Jewels | B58: 134/3 Rani Jhansi Road | C58: Civil Lines | D58: =IFERROR(VLOOKUP(A58, Sheet2!A:B, 2, FALSE), "") | E58: Ludhiana | F58: 03AAZFA6625L1ZZ | G58: AAZFA6625L | H58: PUNJAB | I58: 141001 | J58: Ludhiana
A59: Amrit Plastic | B59: NEW PREET NAGAR, | C59: TIBBA ROAD, | D59: =IFERROR(VLOOKUP(A59, Sheet2!A:B, 2, FALSE), "") | E59: Ludhiana | F59: 03AMSPS6352B1ZZ | G59: AMSPS6352B | H59: PUNJAB | I59: 141001 | J59: Ludhiana
A60: Amrit Shawls | B60: B-viii-557 | C60: Mochpura Bazar | D60: =IFERROR(VLOOKUP(A60, Sheet2!A:B, 2, FALSE), "") | E60: Ludhiana | F60: 03AEFPS6634H1ZG | G60: AEFPS6634H | H60: PUNJAB | I60: 141008 | J60: Ludhiana
A61: Anand And Company | B61: Ashanagar | C61: Sohsarai | D61: =IFERROR(VLOOKUP(A61, Sheet2!A:B, 2, FALSE), "") -> 8709914084 | E61: Biharsharif | F61: 10NEUPK5644K1ZU | G61: NEUPK5644K | H61: BIHAR | I61: 803118 | J61: Nalanda
A62: Anand Crazy Fashion | B62: 668 MALI GANJ LUDHIANA | D62: =IFERROR(VLOOKUP(A62, Sheet2!A:B, 2, FALSE), "") | E62: Ludhiana | F62: 03BERPS1108B1ZW | G62: BERPS1108B | H62: PUNJAB | I62: 141007 | J62: Ludhiana
A63: Anand Enterprises. | B63: Anand Enterprises | D63: =IFERROR(VLOOKUP(A63, Sheet2!A:B, 2, FALSE), "") | E63: Khanna | F63: 03AJCPK3775F1ZG | G63: AJCPK3775F | H63: PUNJAB | I63: 141401 | J63: Ludhiana
A64: Anand Palace | B64: Shop No. 17 | C64: Anand Palace | D64: =IFERROR(VLOOKUP(A64, Sheet2!A:B, 2, FALSE), "") -> 9815484107 | E64: Old Sabzi Mandi | F64: 03ABCFA3238M1ZN | G64: ABCFA3238M | H64: PUNJAB | I64: 141007 | J64: Ludhiana
A65: Aneja Sons Platinum Store | B65: 648/11 | D65: =IFERROR(VLOOKUP(A65, Sheet2!A:B, 2, FALSE), "") | E65: Roorkee | F65: 05AANPA7660B1Z2 | G65: AANPA7660B | H65: UTTRAKHAND | I65: 247667 | J65: Haridwar
A66: Anikha Garments | B66: 7/2A LUCKY NAGAR | C66: Theerth Tower | D66: =IFERROR(VLOOKUP(A66, Sheet2!A:B, 2, FALSE), "") -> 9787938139 | E66: Tiruppur | F66: 33ABUFA6679G1ZW | G66: ABUFA6679G | H66: TAMIL NADU | I66: 641603 | J66: Tiruppur
A67: Anikha Garments (Shipping) | B67: D/251b Anbu Nagar Amman Koil | C67: Thotham, Gobi Road | D67: =IFERROR(VLOOKUP(A67, Sheet2!A:B, 2, FALSE), "") | E67: Kunnathur | F67: 33ABUFA6679G1ZW | G67: ABUFA6679G | H67: TAMIL NADU | I67: 638103
A68: Anil International | B68: SF 5/184B4, KARUKKANKATTUPUDUR | C68: PERUMANALLAUR, TIRRUPUR | D68: =IFERROR(VLOOKUP(A68, Sheet2!A:B, 2, FALSE), "") | E68: Tiruppur | F68: 33ABKFA2461Q1Z5 | G68: ABKFA2461Q | H68: TAMIL NADU | I68: 641666
A69: Anirudh Bags | B69: H.no.302 | C69: Bhagwanganj | D69: =IFERROR(VLOOKUP(A69, Sheet2!A:B, 2, FALSE), "") -> 7610076008 | E69: Ajmer | F69: 08BOBPA2704R1ZY | G69: BOBPA2704R | H69: RAJASTHAN | I69: 305001 | J69: Ajmer
A70: Ankur Carrier | D70: =IFERROR(VLOOKUP(A70, Sheet2!A:B, 2, FALSE), "") | F70: 88AAQPY2517A1ZJ | G70: AAQPY2517A
A71: Ankur Collection | B71: Sadar Bazar | D71: =IFERROR(VLOOKUP(A71, Sheet2!A:B, 2, FALSE), "") | E71: Sultanpur Lodhi | F71: 03AASPM1119L1ZM | G71: AASPM1119L | H71: PUNJAB | I71: 144626 | J71: Kapurthala
A72: Annapurna Industries | B72: Rampura Road | C72: Gill Kalan | D72: =IFERROR(VLOOKUP(A72, Sheet2!A:B, 2, FALSE), "") -> 7009413371 | E72: Gill Kalan | F72: 03PHUPS6283K1Z4 | G72: PHUPS6283K | H72: PUNJAB | I72: 151103 | J72: Bathinda
A73: Anshul Garg S/o Sh. Ashok Kumar | B73: Guru Harkrishan Nagar | D73: =IFERROR(VLOOKUP(A73, Sheet2!A:B, 2, FALSE), "") | E73: Khanna | G73: BXQPG4929N | H73: PUNJAB | I73: 141401 | J73: Ludhiana
A74: Anuj Packaging & Printing Solution | B74: Plot No-114 Raj Nagar-b | C74: C/o Machhla Devi W/o Shri Jai Ram Singh | D74: =IFERROR(VLOOKUP(A74, Sheet2!A:B, 2, FALSE), "") | E74: Agra | F74: 09AIPPC3120N3Z3 | G74: AIPPC3120N | H74: UTTAR PRADESH | I74: 282001 | J74: Agra
A75: Anuj Packers | B75: Anuj Packers | C75: 1977/2 | D75: =IFERROR(VLOOKUP(A75, Sheet2!A:B, 2, FALSE), "") | E75: Opp Water Tank Park | F75: 03BTIPG8827R1Z1 | G75: BTIPG8827R | H75: PUNJAB | I75: 141003 | J75: Ludhiana
A76: Anupam | B76: Sharda Narayan Hospital | C76: Azamgarh Mau Road | D76: =IFERROR(VLOOKUP(A76, Sheet2!A:B, 2, FALSE), "") | E76: Maunath Bhanjan | F76: 09ABYFA6212H1Z4 | G76: ABYFA6212H | H76: UTTAR PRADESH | I76: 275101 | J76: Mau
A77: Apsara Saree Emporium (Sagar) | B77: JAIN DHARAMSHALA SHOP,B.T.GANJ | D77: =IFERROR(VLOOKUP(A77, Sheet2!A:B, 2, FALSE), "") | E77: Roorkee | F77: 05ADJPK2761Q1Z3 | G77: ADJPK2761Q | H77: UTTRAKHAND | I77: 247667 | J77: Haridwar
A78: Arbaj Ansari | D78: =IFERROR(VLOOKUP(A78, Sheet2!A:B, 2, FALSE), "") | H78: PUNJAB
A79: Arora General Store | B79: Old Bank Road, Dasuya | D79: =IFERROR(VLOOKUP(A79, Sheet2!A:B, 2, FALSE), "") -> 9878044566 | E79: Dasuya | F79: 03AALPA8007E1ZB | G79: AALPA8007E | H79: PUNJAB | I79: 144205 | J79: Hoshiarpur
A80: Arora Sports Sangrur | B80: M/s Arora Sports | D80: =IFERROR(VLOOKUP(A80, Sheet2!A:B, 2, FALSE), "") | E80: Sangrur | F80: 03ADRPA9941Q1ZX | G80: ADRPA9941Q | H80: PUNJAB | I80: 148001 | J80: Sangrur
A81: Artistic Art Press | B81: Shop No 5-6-7 Sidhu Complex | C81: Kochar Market | D81: =IFERROR(VLOOKUP(A81, Sheet2!A:B, 2, FALSE), "") | E81: Ludhiana | F81: 03AQAPS6595G1ZM | G81: AQAPS6595G | H81: PUNJAB | I81: 141001 | J81: Ludhiana
A82: Arushi Knitwear | B82: Hadbast No 161 | C82: Abadi Dying Complex | D82: =IFERROR(VLOOKUP(A82, Sheet2!A:B, 2, FALSE), "") | E82: Ludhiana | F82: 03HHUPS3172R1Z8 | G82: HHUPS3172R | H82: PUNJAB | I82: 141008 | J82: Ludhiana
A83: Arvind | D83: =IFERROR(VLOOKUP(A83, Sheet2!A:B, 2, FALSE), "") | E83: Khanna
A84: Asha Collection | D84: =IFERROR(VLOOKUP(A84, Sheet2!A:B, 2, FALSE), "") | E84: Mohalla Soodan | F84: 03ADDPK8840Q1Z5 | G84: ADDPK8840Q | H84: PUNJAB | I84: 141008 | J84: Ludhiana
A85: Ashish Garg | D85: =IFERROR(VLOOKUP(A85, Sheet2!A:B, 2, FALSE), "") | H85: PUNJAB
A86: Ashok Kumar Garg S/o Sh. Hardwari Lal | D86: =IFERROR(VLOOKUP(A86, Sheet2!A:B, 2, FALSE), "")
A87: Ashoka Hosiery Pvt. Ltd. | B87: OFFICE-B-XX1V-4634, ST.NO.06, | C87: SUNDER NAGAR,Rahon Road | D87: 7307303042 | E87: Ludhiana | F87: 03AAECA3722E1ZD | G87: AAECA3722E | H87: PUNJAB | I87: 141007 | J87: Ludhiana
A88: At Candid Shoes | B88: Onr Building Polo | C88: Pynthorbah Block Iii | D88: =IFERROR(VLOOKUP(A88, Sheet2!A:B, 2, FALSE), "") | E88: East Khasi Hills | F88: 17ALFPT3500L1ZZ | G88: ALFPT3500L | H88: MEGHALYA | I88: 793001 | J88: East Khasi Hills
A89: Atam Gian Knitters | B89: B-xxiv-2683 | C89: Sunder nagar | D89: =IFERROR(VLOOKUP(A89, Sheet2!A:B, 2, FALSE), "") | E89: Ludhiana | F89: 03ADWPJ8791J1ZR | G89: ADWPJ8791J | H89: PUNJAB | I89: 141007 | J89: Ludhiana
A90: Atam Prakash & Sons | B90: 110,BT GANJ | D90: =IFERROR(VLOOKUP(A90, Sheet2!A:B, 2, FALSE), "") | E90: Roorkee | F90: 05AACFA6171C1Z0 | G90: AACFA6171C | H90: UTTRAKHAND | I90: 247667 | J90: Haridwar
A91: Atc Supply Chain Solutions Private Limite | B91: 13b Rauz Avenue | C91: Chandra Shekhar Bhawan | D91: =IFERROR(VLOOKUP(A91, Sheet2!A:B, 2, FALSE), "") | E91: New Delhi | F91: 07AAJCA3429K1ZJ | G91: AAJCA3429K | H91: DELHI | I91: 110002 | J91: Central Delhi
A92: Attidude Garments | B92: 29 Katchaleeswarar Garden Street | C92: Muthialpet | D92: =IFERROR(VLOOKUP(A92, Sheet2!A:B, 2, FALSE), "") | E92: Chennai | F92: 33AWDPK8437A1ZV | G92: AWDPK8437A | H92: TAMIL NADU | I92: 600001 | J92: Chennai
A93: Attitude | B93: Main Road | D93: =IFERROR(VLOOKUP(A93, Sheet2!A:B, 2, FALSE), "") | E93: Kasia | F93: 09CABPS3246P1Z3 | G93: CABPS3246P | H93: UTTAR PRADESH | I93: 274402 | J93: Kushinagar
A94: Audit Fee Payable | D94: =IFERROR(VLOOKUP(A94, Sheet2!A:B, 2, FALSE), "")
A95: Avg Packaging | B95: Rect.no-19, Kila No-12/1 | C95: Khewat/khata No-80/102 | D95: =IFERROR(VLOOKUP(A95, Sheet2!A:B, 2, FALSE), "") | E95: Gurugram | F95: 06ACDFA9965H1Z3 | G95: ACDFA9965H | H95: HARYANA | I95: 122004 | J95: Gurugram
A96: Avinash Fancy Store | B96: Talab Bazar | D96: =IFERROR(VLOOKUP(A96, Sheet2!A:B, 2, FALSE), "") | E96: Malerkotla | F96: 03AGNPK5433A1ZV | G96: AGNPK5433A | H96: PUNJAB | I96: 148023 | J96: Sangrur
A97: Avtar Agencies | B97: Sco No.31,phase-iv | D97: =IFERROR(VLOOKUP(A97, Sheet2!A:B, 2, FALSE), "") | E97: Ludhiana | F97: 03ABOFA8946J1Z0 | G97: ABOFA8946J | H97: PUNJAB | I97: 141014 | J97: Ludhiana
A98: B.m. Exports | B98: Ix-3648 | C98: Near Satya Narain Mandir | D98: =IFERROR(VLOOKUP(A98, Sheet2!A:B, 2, FALSE), "") | E98: Delhi | F98: 07AAAFB8137F1ZP | G98: AAAFB8137F | H98: DELHI | I98: 110031 | J98: East Delhi
A99: B.p. Art Press | B99: ST NO. 6 9983-1 RANJIT SINGH NAGAR | C99: Gill Road | D99: =IFERROR(VLOOKUP(A99, Sheet2!A:B, 2, FALSE), "") -> 8801111104 | E99: Ludhiana | F99: 03ACCPK3074A1ZD | G99: ACCPK3074A | H99: PUNJAB | I99: 141001 | J99: Ludhiana
A100: BL Oswal Hosiery | B100: 127/295 U-block, Second Scheame | D100: =IFERROR(VLOOKUP(A100, Sheet2!A:B, 2, FALSE), "") | E100: Kanpur | F100: 09ABOPL3357N1ZX | G100: ABOPL3357N | H100: UTTAR PRADESH | I100: 208014 | J100: Kanpur Nagar
A101: Babloo Garments | B101: 4 PT.RAJA RAM GALI | C101: Jagadhri Road | D101: =IFERROR(VLOOKUP(A101, Sheet2!A:B, 2, FALSE), "") | E101: Yamunanagar | F101: 06APQPS3799M1ZP | G101: APQPS3799M | H101: HARYANA | I101: 135001 | J101: Yamunanagar
...

Sheet Sheet2
A1: AASTHA MARKETING | B1: 9993560225 | C1: Agent | D1: A | E1: Parminder
A2: ABAAN PACKAGING | B2: 9825776004 | C2: Agent | D2: A | E2: Jyoti
A3: AIRA KNITWEARS | B3: 8360316861 | C3: Customer | D3: A | E3: RAVI LDH
A4: AJAY BAGS MANUFACTURER | B4: 8250125512 | C4: Agent | D4: A | E4: Parminder
A5: AJEET ARTS | B5: 9820427369 | C5: Customer | D5: A | E5: Purchase
A6: AJIT MILLS (AMS) | B6: 9261240004 | C6: Customer | D6: A | E6: Dinesh
A7: AKANKSHA FABRICS | B7: 9779160685 | C7: Customer | D7: A | E7: Dinesh
A8: AL QAMAR GRAPHICS | B8: 9103101774 | C8: Agent | D8: A | E8: Parminder
A9: AMAR GARMENTS AND JEWELLERY | B9: 8676885999 | C9: Customer | D9: A | E9: Jyoti
A10: AMIN- BIN-KHALIK IMPEX (ABK IMPEX) | B10: 9906598692 | C10: Customer | D10: A | E10: Gourav
A11: ANAND AND COMPANY | B11: 8709914084 | C11: Agent | D11: A | E11: Parminder
A12: ANAND PALACE | B12: 9815484107 | C12: Customer | D12: A | E12: Dinesh
... A24: BALA JI BAGS AND PRINTING | B24: 6200506453 | C24: Agent | D24: A | E24: Parminder
A25: BANSAL NEW KKC | B25: 0000000000 | C25: Customer | D25: B | E25: Parminder
A26: BANSAL POLYMER | B26: 9803400071 | C26: Agent | D26: A | E26: Parminder
A27: BATRA GARMENTS PRIVATE LIMITED | B27: 9268116660 | C27: Customer | D27: A | E27: Parminder
A28: BATRA SILK AND SAREE | B28: 9872851000 | C28: Customer | D28: A | E28: Dinesh
A29: BATRA SILK STORE | B29: 9876600010 | C29: Customer | D29: A | E29: Dinesh
A30: BATTU PLAZA | B30: 7696664616 | C30: Customer | D30: A | E30: Purchase
A31: BAWA LEATHER POINT | B31: 9872492217 | C31: Customer | D31: A | E31: Gourav
A32: BEDI FASHION SHOPPEE | B32: 9876240929 | C32: Customer | D32: A | E32: RAVI LDH
A33: BEDI WORLD FASHION | B33: 9988009536 | C33: Customer | D33: A | E33: RAVI LDH
A34: BHAPE DI HATTI | B34: 9780234696 | C34: Customer | D34: A | E34: RAVI LDH
A35: BHARGAVA SHOES | B35: 9041930007 | C35: Customer | D35: A | E35: Parminder
A36: BHOMIA HOSIERY MILLS | B36: 9915117722 | C36: Customer | D36: A | E36: Jyoti
A37: BHOOMI INTERNATIONAL | B37: 9896042097 | C37: Customer | D37: A | E37: Parminder
... A250: ZIAMA FASHIONS PVT LTD | B250: 9876004495 | C250: Customer | D250: A | E250: RAVI LDH
